{
  "retCode": 0,
  "retMsg": "success",
  "result": {
    "yieldTrend": [
      {
        "statisticDate": "1766880000000",
        "yieldE8": "24856229046",
        "totalYieldE8": "704560803697",
        "totalYieldRateE4": "21620",
        "yieldRateE4": "274",
        "curShardProfitE8": "0",
        "curClosedPnlE8": "0",
        "cumResetRoiE4": "274",
        "cumResetPnlE8": "24856229046",
        "trendValue": "0",
        "cycleRealizedPnlE8": "24021629046",
        "cycleUnrealizedPnlChangeE8": "834599999",
        "yieldBotE8": "0",
        "cycleRealizedPnlBotE8": "0",
        "cycleUnrealizedPnlChangeBotE8": "0",
        "yieldAllE8": "24856229046",
        "cycleRealizedPnlAllE8": "24021629046",
        "cycleUnrealizedPnlChangeAllE8": "834599999"
      },
      {
        "statisticDate": "1766966400000",
        "yieldE8": "26703369488",
        "totalYieldE8": "731299723130",
        "totalYieldRateE4": "22438",
        "yieldRateE4": "286",
        "curShardProfitE8": "0",
        "curClosedPnlE8": "0",
        "cumResetRoiE4": "568",
        "cumResetPnlE8": "51559598534",
        "trendValue": "0",
        "cycleRealizedPnlE8": "26748369488",
        "cycleUnrealizedPnlChangeE8": "-45000000",
        "yieldBotE8": "0",
        "cycleRealizedPnlBotE8": "0",
        "cycleUnrealizedPnlChangeBotE8": "0",
        "yieldAllE8": "26703369488",
        "cycleRealizedPnlAllE8": "26748369488",
        "cycleUnrealizedPnlChangeAllE8": "-45000000"
      },
      {
        "statisticDate": "1767052800000",
        "yieldE8": "14272640024",
        "totalYieldE8": "746104618662",
        "totalYieldRateE4": "22876",
        "yieldRateE4": "148",
        "curShardProfitE8": "0",
        "curClosedPnlE8": "0",
        "cumResetRoiE4": "726",
        "cumResetPnlE8": "65832238558",
        "trendValue": "0",
        "cycleRealizedPnlE8": "14749264024",
        "cycleUnrealizedPnlChangeE8": "-476624000",
        "yieldBotE8": "0",
        "cycleRealizedPnlBotE8": "0",
        "cycleUnrealizedPnlChangeBotE8": "0",
        "yieldAllE8": "14272640024",
        "cycleRealizedPnlAllE8": "14749264024",
        "cycleUnrealizedPnlChangeAllE8": "-476624000"
      },
      {
        "statisticDate": "1767139200000",
        "yieldE8": "36130463523",
        "totalYieldE8": "781702825788",
        "totalYieldRateE4": "23983",
        "yieldRateE4": "371",
        "curShardProfitE8": "0",
        "curClosedPnlE8": "0",
        "cumResetRoiE4": "1124",
        "cumResetPnlE8": "101962702081",
        "trendValue": "0",
        "cycleRealizedPnlE8": "35653839523",
        "cycleUnrealizedPnlChangeE8": "476624000",
        "yieldBotE8": "0",
        "cycleRealizedPnlBotE8": "0",
        "cycleUnrealizedPnlChangeBotE8": "0",
        "yieldAllE8": "36130463523",
        "cycleRealizedPnlAllE8": "35653839523",
        "cycleUnrealizedPnlChangeAllE8": "476624000"
      },
      {
        "statisticDate": "1767225600000",
        "yieldE8": "17191265178",
        "totalYieldE8": "798894106636",
        "totalYieldRateE4": "24510",
        "yieldRateE4": "170",
        "curShardProfitE8": "0",
        "curClosedPnlE8": "0",
        "cumResetRoiE4": "1314",
        "cumResetPnlE8": "119153967259",
        "trendValue": "0",
        "cycleRealizedPnlE8": "17191265178",
        "cycleUnrealizedPnlChangeE8": "0",
        "yieldBotE8": "0",
        "cycleRealizedPnlBotE8": "0",
        "cycleUnrealizedPnlChangeBotE8": "0",
        "yieldAllE8": "17191265178",
        "cycleRealizedPnlAllE8": "17191265178",
        "cycleUnrealizedPnlChangeAllE8": "0"
      },
      {
        "statisticDate": "1767312000000",
        "yieldE8": "5395584691",
        "totalYieldE8": "804560324086",
        "totalYieldRateE4": "24676",
        "yieldRateE4": "52",
        "curShardProfitE8": "0",
        "curClosedPnlE8": "0",
        "cumResetRoiE4": "1373",
        "cumResetPnlE8": "124549551950",
        "trendValue": "0",
        "cycleRealizedPnlE8": "5661584691",
        "cycleUnrealizedPnlChangeE8": "-266000000",
        "yieldBotE8": "0",
        "cycleRealizedPnlBotE8": "0",
        "cycleUnrealizedPnlChangeBotE8": "0",
        "yieldAllE8": "5395584691",
        "cycleRealizedPnlAllE8": "5661584691",
        "cycleUnrealizedPnlChangeAllE8": "-266000000"
      },
      {
        "statisticDate": "1767398400000",
        "yieldE8": "11203547106",
        "totalYieldE8": "815750188168",
        "totalYieldRateE4": "25019",
        "yieldRateE4": "108",
        "curShardProfitE8": "0",
        "curClosedPnlE8": "0",
        "cumResetRoiE4": "1497",
        "cumResetPnlE8": "135753099056",
        "trendValue": "0",
        "cycleRealizedPnlE8": "11189547106",
        "cycleUnrealizedPnlChangeE8": "14000000",
        "yieldBotE8": "0",
        "cycleRealizedPnlBotE8": "0",
        "cycleUnrealizedPnlChangeBotE8": "0",
        "yieldAllE8": "11203547106",
        "cycleRealizedPnlAllE8": "11189547106",
        "cycleUnrealizedPnlChangeAllE8": "14000000"
      }
    ],
    "yieldTrendBot": [
      {
        "statisticDate": "1766880000000",
        "yieldE8": "0",
        "totalYieldE8": "0",
        "totalYieldRateE4": "0",
        "yieldRateE4": "0",
        "curShardProfitE8": "0",
        "curClosedPnlE8": "0",
        "cumResetRoiE4": "0",
        "cumResetPnlE8": "0",
        "trendValue": "0",
        "cycleRealizedPnlE8": "0",
        "cycleUnrealizedPnlChangeE8": "0",
        "yieldBotE8": "0",
        "cycleRealizedPnlBotE8": "0",
        "cycleUnrealizedPnlChangeBotE8": "0",
        "yieldAllE8": "24856229046",
        "cycleRealizedPnlAllE8": "24021629046",
        "cycleUnrealizedPnlChangeAllE8": "834599999"
      },
      {
        "statisticDate": "1766966400000",
        "yieldE8": "0",
        "totalYieldE8": "0",
        "totalYieldRateE4": "0",
        "yieldRateE4": "0",
        "curShardProfitE8": "0",
        "curClosedPnlE8": "0",
        "cumResetRoiE4": "0",
        "cumResetPnlE8": "0",
        "trendValue": "0",
        "cycleRealizedPnlE8": "0",
        "cycleUnrealizedPnlChangeE8": "0",
        "yieldBotE8": "0",
        "cycleRealizedPnlBotE8": "0",
        "cycleUnrealizedPnlChangeBotE8": "0",
        "yieldAllE8": "26703369488",
        "cycleRealizedPnlAllE8": "26748369488",
        "cycleUnrealizedPnlChangeAllE8": "-45000000"
      },
      {
        "statisticDate": "1767052800000",
        "yieldE8": "0",
        "totalYieldE8": "0",
        "totalYieldRateE4": "0",
        "yieldRateE4": "0",
        "curShardProfitE8": "0",
        "curClosedPnlE8": "0",
        "cumResetRoiE4": "0",
        "cumResetPnlE8": "0",
        "trendValue": "0",
        "cycleRealizedPnlE8": "0",
        "cycleUnrealizedPnlChangeE8": "0",
        "yieldBotE8": "0",
        "cycleRealizedPnlBotE8": "0",
        "cycleUnrealizedPnlChangeBotE8": "0",
        "yieldAllE8": "14272640024",
        "cycleRealizedPnlAllE8": "14749264024",
        "cycleUnrealizedPnlChangeAllE8": "-476624000"
      },
      {
        "statisticDate": "1767139200000",
        "yieldE8": "0",
        "totalYieldE8": "0",
        "totalYieldRateE4": "0",
        "yieldRateE4": "0",
        "curShardProfitE8": "0",
        "curClosedPnlE8": "0",
        "cumResetRoiE4": "0",
        "cumResetPnlE8": "0",
        "trendValue": "0",
        "cycleRealizedPnlE8": "0",
        "cycleUnrealizedPnlChangeE8": "0",
        "yieldBotE8": "0",
        "cycleRealizedPnlBotE8": "0",
        "cycleUnrealizedPnlChangeBotE8": "0",
        "yieldAllE8": "36130463523",
        "cycleRealizedPnlAllE8": "35653839523",
        "cycleUnrealizedPnlChangeAllE8": "476624000"
      },
      {
        "statisticDate": "1767225600000",
        "yieldE8": "0",
        "totalYieldE8": "0",
        "totalYieldRateE4": "0",
        "yieldRateE4": "0",
        "curShardProfitE8": "0",
        "curClosedPnlE8": "0",
        "cumResetRoiE4": "0",
        "cumResetPnlE8": "0",
        "trendValue": "0",
        "cycleRealizedPnlE8": "0",
        "cycleUnrealizedPnlChangeE8": "0",
        "yieldBotE8": "0",
        "cycleRealizedPnlBotE8": "0",
        "cycleUnrealizedPnlChangeBotE8": "0",
        "yieldAllE8": "17191265178",
        "cycleRealizedPnlAllE8": "17191265178",
        "cycleUnrealizedPnlChangeAllE8": "0"
      },
      {
        "statisticDate": "1767312000000",
        "yieldE8": "0",
        "totalYieldE8": "0",
        "totalYieldRateE4": "0",
        "yieldRateE4": "0",
        "curShardProfitE8": "0",
        "curClosedPnlE8": "0",
        "cumResetRoiE4": "0",
        "cumResetPnlE8": "0",
        "trendValue": "0",
        "cycleRealizedPnlE8": "0",
        "cycleUnrealizedPnlChangeE8": "0",
        "yieldBotE8": "0",
        "cycleRealizedPnlBotE8": "0",
        "cycleUnrealizedPnlChangeBotE8": "0",
        "yieldAllE8": "5395584691",
        "cycleRealizedPnlAllE8": "5661584691",
        "cycleUnrealizedPnlChangeAllE8": "-266000000"
      },
      {
        "statisticDate": "1767398400000",
        "yieldE8": "0",
        "totalYieldE8": "0",
        "totalYieldRateE4": "0",
        "yieldRateE4": "0",
        "curShardProfitE8": "0",
        "curClosedPnlE8": "0",
        "cumResetRoiE4": "0",
        "cumResetPnlE8": "0",
        "trendValue": "0",
        "cycleRealizedPnlE8": "0",
        "cycleUnrealizedPnlChangeE8": "0",
        "yieldBotE8": "0",
        "cycleRealizedPnlBotE8": "0",
        "cycleUnrealizedPnlChangeBotE8": "0",
        "yieldAllE8": "11203547106",
        "cycleRealizedPnlAllE8": "11189547106",
        "cycleUnrealizedPnlChangeAllE8": "14000000"
      }
    ],
    "yieldTrendAll": [
      {
        "statisticDate": "1766880000000",
        "yieldE8": "24856229046",
        "totalYieldE8": "0",
        "totalYieldRateE4": "0",
        "yieldRateE4": "274",
        "curShardProfitE8": "0",
        "curClosedPnlE8": "0",
        "cumResetRoiE4": "274",
        "cumResetPnlE8": "24856229046",
        "trendValue": "0",
        "cycleRealizedPnlE8": "24021629046",
        "cycleUnrealizedPnlChangeE8": "834599999",
        "yieldBotE8": "0",
        "cycleRealizedPnlBotE8": "0",
        "cycleUnrealizedPnlChangeBotE8": "0",
        "yieldAllE8": "24856229046",
        "cycleRealizedPnlAllE8": "24021629046",
        "cycleUnrealizedPnlChangeAllE8": "834599999"
      },
      {
        "statisticDate": "1766966400000",
        "yieldE8": "26703369488",
        "totalYieldE8": "0",
        "totalYieldRateE4": "0",
        "yieldRateE4": "286",
        "curShardProfitE8": "0",
        "curClosedPnlE8": "0",
        "cumResetRoiE4": "568",
        "cumResetPnlE8": "51559598534",
        "trendValue": "0",
        "cycleRealizedPnlE8": "26748369488",
        "cycleUnrealizedPnlChangeE8": "-45000000",
        "yieldBotE8": "0",
        "cycleRealizedPnlBotE8": "0",
        "cycleUnrealizedPnlChangeBotE8": "0",
        "yieldAllE8": "26703369488",
        "cycleRealizedPnlAllE8": "26748369488",
        "cycleUnrealizedPnlChangeAllE8": "-45000000"
      },
      {
        "statisticDate": "1767052800000",
        "yieldE8": "14272640024",
        "totalYieldE8": "0",
        "totalYieldRateE4": "0",
        "yieldRateE4": "148",
        "curShardProfitE8": "0",
        "curClosedPnlE8": "0",
        "cumResetRoiE4": "726",
        "cumResetPnlE8": "65832238558",
        "trendValue": "0",
        "cycleRealizedPnlE8": "14749264024",
        "cycleUnrealizedPnlChangeE8": "-476624000",
        "yieldBotE8": "0",
        "cycleRealizedPnlBotE8": "0",
        "cycleUnrealizedPnlChangeBotE8": "0",
        "yieldAllE8": "14272640024",
        "cycleRealizedPnlAllE8": "14749264024",
        "cycleUnrealizedPnlChangeAllE8": "-476624000"
      },
      {
        "statisticDate": "1767139200000",
        "yieldE8": "36130463523",
        "totalYieldE8": "0",
        "totalYieldRateE4": "0",
        "yieldRateE4": "371",
        "curShardProfitE8": "0",
        "curClosedPnlE8": "0",
        "cumResetRoiE4": "1124",
        "cumResetPnlE8": "101962702081",
        "trendValue": "0",
        "cycleRealizedPnlE8": "35653839523",
        "cycleUnrealizedPnlChangeE8": "476624000",
        "yieldBotE8": "0",
        "cycleRealizedPnlBotE8": "0",
        "cycleUnrealizedPnlChangeBotE8": "0",
        "yieldAllE8": "36130463523",
        "cycleRealizedPnlAllE8": "35653839523",
        "cycleUnrealizedPnlChangeAllE8": "476624000"
      },
      {
        "statisticDate": "1767225600000",
        "yieldE8": "17191265178",
        "totalYieldE8": "0",
        "totalYieldRateE4": "0",
        "yieldRateE4": "170",
        "curShardProfitE8": "0",
        "curClosedPnlE8": "0",
        "cumResetRoiE4": "1314",
        "cumResetPnlE8": "119153967259",
        "trendValue": "0",
        "cycleRealizedPnlE8": "17191265178",
        "cycleUnrealizedPnlChangeE8": "0",
        "yieldBotE8": "0",
        "cycleRealizedPnlBotE8": "0",
        "cycleUnrealizedPnlChangeBotE8": "0",
        "yieldAllE8": "17191265178",
        "cycleRealizedPnlAllE8": "17191265178",
        "cycleUnrealizedPnlChangeAllE8": "0"
      },
      {
        "statisticDate": "1767312000000",
        "yieldE8": "5395584691",
        "totalYieldE8": "0",
        "totalYieldRateE4": "0",
        "yieldRateE4": "52",
        "curShardProfitE8": "0",
        "curClosedPnlE8": "0",
        "cumResetRoiE4": "1373",
        "cumResetPnlE8": "124549551950",
        "trendValue": "0",
        "cycleRealizedPnlE8": "5661584691",
        "cycleUnrealizedPnlChangeE8": "-266000000",
        "yieldBotE8": "0",
        "cycleRealizedPnlBotE8": "0",
        "cycleUnrealizedPnlChangeBotE8": "0",
        "yieldAllE8": "5395584691",
        "cycleRealizedPnlAllE8": "5661584691",
        "cycleUnrealizedPnlChangeAllE8": "-266000000"
      },
      {
        "statisticDate": "1767398400000",
        "yieldE8": "11203547106",
        "totalYieldE8": "0",
        "totalYieldRateE4": "0",
        "yieldRateE4": "108",
        "curShardProfitE8": "0",
        "curClosedPnlE8": "0",
        "cumResetRoiE4": "1497",
        "cumResetPnlE8": "135753099056",
        "trendValue": "0",
        "cycleRealizedPnlE8": "11189547106",
        "cycleUnrealizedPnlChangeE8": "14000000",
        "yieldBotE8": "0",
        "cycleRealizedPnlBotE8": "0",
        "cycleUnrealizedPnlChangeBotE8": "0",
        "yieldAllE8": "11203547106",
        "cycleRealizedPnlAllE8": "11189547106",
        "cycleUnrealizedPnlChangeAllE8": "14000000"
      }
    ]
  },
  "retExtInfo": {},
  "time": 1767560747805
}